mikegrad/__init__.py
mikegrad/engine.py
mikegrad/nn.py
mikegrad-0.1.0.dist-info/LICENSE
mikegrad-0.1.0.dist-info/METADATA
mikegrad-0.1.0.dist-info/WHEEL
mikegrad-0.1.0.dist-info/top_level.txt
mikegrad-0.1.0.dist-info/RECORD
