Metadata-Version: 2.2
Name: mikegrad
Version: 0.1.0
Summary: A minimal autograd engine
Home-page: https://github.com/canmike/mikegrad
Author: Can Michael Hucko
Author-email: c.michaelhucko@gmail.com
Classifier: Programming Language :: Python :: 3
Classifier: License :: OSI Approved :: MIT License
Classifier: Operating System :: OS Independent
Requires-Python: >=3.6
License-File: LICENSE
Requires-Dist: numpy>=1.19.0
Dynamic: author
Dynamic: author-email
Dynamic: classifier
Dynamic: description
Dynamic: description-content-type
Dynamic: home-page
Dynamic: requires-dist
Dynamic: requires-python
Dynamic: summary
